evengsdk/__init__.py
evengsdk/__main__.py
evengsdk/api.py
evengsdk/client.py
evengsdk/exceptions.py
evengsdk/templates.py
evengsdk/cli/__init__.py
evengsdk/cli/cli.py
evengsdk/cli/common.py
evengsdk/cli/console.py
evengsdk/cli/utils.py
evengsdk/cli/version.py
evengsdk/cli/folders/__init__.py
evengsdk/cli/folders/commands.py
evengsdk/cli/lab/__init__.py
evengsdk/cli/lab/commands.py
evengsdk/cli/lab/topology.py
evengsdk/cli/node/__init__.py
evengsdk/cli/node/commands.py
evengsdk/cli/system/__init__.py
evengsdk/cli/system/commands.py
evengsdk/cli/users/__init__.py
evengsdk/cli/users/commands.py
evengsdk/plugins/__init__.py
evengsdk/plugins/display.py
evengsdk/schemas/__init__.py
evengsdk/schemas/lab-schema.json
evengsdk/schemas/validator.py
tests/__init__.py
tests/conftest.py
tests/test_api_client.py
tests/test_topology_schemas.py
tests/api/__init__.py
tests/api/conftest.py
tests/api/test_api.py
tests/api/test_api_lab.py
tests/api/test_api_network.py
tests/api/test_api_nodes.py
tests/api/test_api_user.py
tests/cli/__init__.py
tests/cli/conftest.py
tests/cli/test_cli.py
tests/cli/test_cli_folder.py
tests/cli/test_cli_lab.py
tests/cli/test_cli_node.py
tests/cli/test_cli_system.py
tests/cli/test_cli_user.py
eve_ng-0.2.7.dist-info/LICENSE
eve_ng-0.2.7.dist-info/METADATA
eve_ng-0.2.7.dist-info/WHEEL
eve_ng-0.2.7.dist-info/entry_points.txt
eve_ng-0.2.7.dist-info/top_level.txt
eve_ng-0.2.7.dist-info/RECORD
