Metadata-Version: 2.1
Name: eve-ng
Version: 0.2.7
Summary: Python SDK and command line utilities to work with the EVE-NG REST API
Home-page: https://github.com/ttafsir/evengsdk
Author: Tafsir Thiam
Author-email: ttafsir@gmail.com
License: MIT license
Keywords: eve-ng,eveng,unetlab,evengsdk
Platform: UNKNOWN
Classifier: Development Status :: 3 - Alpha
Classifier: Intended Audience :: Developers
Classifier: License :: OSI Approved :: MIT License
Classifier: Natural Language :: English
Classifier: Programming Language :: Python :: 3
Classifier: Programming Language :: Python :: 3.7
Classifier: Programming Language :: Python :: 3.8
Classifier: Programming Language :: Python :: 3.9
Requires-Python: >=3.7
License-File: LICENSE
Requires-Dist: click (<8.1.0,>=7.1.1)
Requires-Dist: requests (>=2.20.0)
Requires-Dist: python-dotenv
Requires-Dist: pyyaml (<7.0,>=5.3)
Requires-Dist: Jinja2 (<3.1.0,>=2.10.3)
Requires-Dist: rich (==10.16.2)
Requires-Dist: jsonschema (==4.3.3)
